{
    "version": "0.2",
    "ignorePaths": [],
    "dictionaryDefinitions": [],
    "dictionaries": [],
    "words": [
        "Akkoyun",
        "atmelavr",
        "atmelmegaavr",
        "AUTOBND",
        "CCID",
        "CCLK",
        "CGACT",
        "CGDCONT",
        "CGPADDR",
        "CGREG",
        "CGSN",
        "CMEE",
        "COMPA",
        "compatable",
        "CPIN",
        "CREG",
        "CTZU",
        "DDRJ",
        "ETSI",
        "FCLASS",
        "GPIO",
        "GPRS",
        "Gunce",
        "HTTPCFG",
        "HTTPRCV",
        "HTTPSND",
        "ICCID",
        "IMEI",
        "Mehmet",
        "mgbs",
        "millis",
        "NITZ",
        "OCIE",
        "OTASETRI",
        "PCICR",
        "PCINT",
        "PCMSK",
        "PINJ",
        "PORTH",
        "PORTJ",
        "PSMRI",
        "REGMODE",
        "RSSI",
        "SCFG",
        "SCFGEXT",
        "SERVIFO",
        "SERVINFO",
        "SGACT",
        "SGACTCFG",
        "SHDN",
        "SLRI",
        "SLUDP",
        "SMSRI",
        "SRECV",
        "SRING",
        "SSEND",
        "TCCR",
        "TCNT",
        "Telit",
        "TIMSK",
        "Turkcell",
        "TXMON",
        "TXMONMODE",
        "vect"
    ],
    "ignoreWords": [],
    "import": []
}
